sage_book_server/__init__.py
sage_book_server/entrypoint.py
sage_book_server/bin/sage-book-server
sage_book_server-0.1.2.dist-info/METADATA
sage_book_server-0.1.2.dist-info/WHEEL
sage_book_server-0.1.2.dist-info/entry_points.txt
sage_book_server-0.1.2.dist-info/top_level.txt
sage_book_server-0.1.2.dist-info/RECORD
