Metadata-Version: 2.4
Name: sage-book-server
Version: 0.1.2
Summary: Sage Book Server Package
Author-email: AlpineX Labs <team@multiplyr.xyz>
Project-URL: Homepage, https://alpinex.ai
Project-URL: Bug Tracker, https://github.com/AlpineX-Labs/
Classifier: Programming Language :: Python :: 3
Classifier: License :: OSI Approved :: MIT License
Classifier: Operating System :: OS Independent
Requires-Python: >=3.10
Requires-Dist: mcp[cli]
Requires-Dist: python-dotenv
Requires-Dist: anthropic
Requires-Dist: requests
Requires-Dist: jupyterlab
Requires-Dist: jupyter-collaboration
Requires-Dist: ipykernel
Requires-Dist: nbformat
Requires-Dist: nbclient
Requires-Dist: pandas
Requires-Dist: matplotlib
Requires-Dist: numpy
Requires-Dist: seaborn
Requires-Dist: scipy
Requires-Dist: scikit-learn
Requires-Dist: plotly
Requires-Dist: yfinance
Requires-Dist: fuzzywuzzy
Requires-Dist: python-Levenshtein
Requires-Dist: statsmodels
Requires-Dist: sqlalchemy
Requires-Dist: psycopg2-binary
